wf4bwdf/__init__.py
wf4bwdf/_data_loading.py
wf4bwdf/_solution_evaluation.py
wf4bwdf/_solutions_loading.py
wf4bwdf/data/InflowData.xlsx
wf4bwdf/data/WeatherData.xlsx
wf4bwdf/py.typed
wf4bwdf-1.0.0.dist-info/licenses/LICENSE
wf4bwdf-1.0.0.dist-info/WHEEL
wf4bwdf-1.0.0.dist-info/METADATA
wf4bwdf-1.0.0.dist-info/RECORD
