Metadata-Version: 2.4
Name: wf4bwdf
Version: 1.0.0
Summary: Water-Futures Team's implementation of the Battle of the Water Demand Forecasting
Keywords: water,water demand,forecasting,urban water systems,battle,competition,battle water networks
Author: S. Alvisi, M. Franchini, V. Marsili, F. Mazzoni, E. Salomons
Author-email: F. Mazzoni <filippo.mazzoni@unife.it>
License-Expression: MIT
License-File: LICENSE
Classifier: Development Status :: 5 - Production/Stable
Classifier: Programming Language :: Python
Classifier: Programming Language :: Python :: 3
Classifier: Programming Language :: Python :: 3.11
Classifier: Programming Language :: Python :: 3.12
Classifier: Programming Language :: Python :: 3.13
Requires-Dist: holidays>=0.81
Requires-Dist: openpyxl>3.1
Requires-Dist: pandas>2.1.0
Maintainer: Dennis Zanutto
Maintainer-email: Dennis Zanutto <dennis.zanutto@polimi.it>
Requires-Python: >=3.11
Project-URL: Documentation, https://github.com/WaterFutures/wf4bwdf#readme
Project-URL: Paper, https://ascelibrary.org/doi/full/10.1061/JWRMD5.WRENG-6887
Project-URL: Paper supplementary information, https://ascelibrary.org/doi/suppl/10.1061/JWRMD5.WRENG-6887/suppl_file/supplemental_materials_jwrmd5.wreng-6887_alvisi.zip
Project-URL: Repository, https://github.com/WaterFutures/wf4bwdf
